pyrutext.py
pyrutext-0.8.0.dist-info/LICENSE
pyrutext-0.8.0.dist-info/WHEEL
pyrutext-0.8.0.dist-info/METADATA
pyrutext-0.8.0.dist-info/RECORD
