Metadata-Version: 2.1
Name: pyrutext
Version: 0.8.0
Summary: A Russian text generator based on templating texts and word picking
Author-email: Belreau Cohen <nuu.chah.nulth@disroot.org>
Classifier: License :: OSI Approved :: MIT License
Requires-Dist: pyyaml ~=6.0
Requires-Dist: aioconsole ~=0.4
Project-URL: Home, https://github.com/Belstowe/py-rutext.git
